odoo/addons/product_isp/__init__.py
odoo/addons/product_isp/__manifest__.py
odoo/addons/product_isp/i18n/product_isp.pot
odoo/addons/product_isp/models/__init__.py
odoo/addons/product_isp/models/product_product.py
odoo/addons/product_isp/static/description/icon.png
odoo/addons/product_isp/static/description/index.html
odoo/addons/product_isp/views/product_product.xml
odoo12_addon_product_isp-12.0.1.0.0.99.dev2.dist-info/METADATA
odoo12_addon_product_isp-12.0.1.0.0.99.dev2.dist-info/WHEEL
odoo12_addon_product_isp-12.0.1.0.0.99.dev2.dist-info/top_level.txt
odoo12_addon_product_isp-12.0.1.0.0.99.dev2.dist-info/RECORD
